{
  "start": "protas-home",
  "storylines": {
    "protas-home": {
      "symbol": "1",
      "label": "Prota's Home",
      "isMissing": true,
      "next": "marbels-lab"
    },

    "marbels-lab": {
      "symbol": "2",
      "label": "Marbel's Lab",
      "isMissing": true,
      "special": "library",
      "normal": "library",
      "fail": "library"
    },

    "library": {
      "symbol": "3",
      "label": "Library",
      "special": "skate-park",
      "normal": "sandwich-shop",
      "fail": "daycare"
    },

    "skate-park": {
      "symbol": "4A",
      "label": "Skate Park",
      "special": "ball-museum",
      "normal": "ball-museum",
      "fail": "ball-museum"
    },
    "sandwich-shop": {
      "symbol": "4B",
      "label": "Sandwich Shop",
      "special": "ball-museum",
      "normal": "ball-museum",
      "fail": "ball-museum"
    },
    "daycare": {
      "symbol": "4C",
      "label": "Daycare",
      "special": "ball-museum",
      "normal": "ball-museum",
      "fail": "ball-museum"
    },

    "ball-museum": {
      "symbol": "5",
      "label": "Ball Museum",
      "special": "security-city",
      "normal": "pickle-yard",
      "fail": "vintage-viper"
    },

    "security-city": {
      "symbol": "6A",
      "label": "Security City",
      "special": "festi-ball",
      "normal": "festi-ball",
      "fail": "festi-ball"
    },
    "pickle-yard": {
      "symbol": "6B",
      "label": "Pickle Yard",
      "special": "festi-ball",
      "normal": "festi-ball",
      "fail": "festi-ball"
    },
    "vintage-viper": {
      "symbol": "6C",
      "label": "Vintage Viper",
      "special": "festi-ball",
      "normal": "festi-ball",
      "fail": "festi-ball"
    },

    "festi-ball": {
      "symbol": "7",
      "label": "Festi-Ball",
      "next": "ending"
    },

    "ending": {
      "symbol": "8",
      "label": "Ending"
    }
  }
}
